ipe/__init__.py
ipe/__main__.py
ipe/fits.py
ipe/helpprint.py
ipe/loop.py
ipe/np_csv.py
ipe/plot.py
ipe/potential_commands.py
ipe/potential_commands_extentions.py
tyjoto_ipe-0.1.2.dist-info/LICENSE
tyjoto_ipe-0.1.2.dist-info/METADATA
tyjoto_ipe-0.1.2.dist-info/WHEEL
tyjoto_ipe-0.1.2.dist-info/entry_points.txt
tyjoto_ipe-0.1.2.dist-info/top_level.txt
tyjoto_ipe-0.1.2.dist-info/RECORD
