Metadata-Version: 2.1
Name: tyjoto-ipe
Version: 0.1.2
Summary: Interactive Plot Editor
Author-email: tyjoto <tyjoto@gmail.com>
License: Apache License
Project-URL: Homepage, https://github.com/tyjoto/ipe
Keywords: ipe,interactive,plot
Classifier: License :: OSI Approved :: Apache Software License
Classifier: Programming Language :: Python
Classifier: Programming Language :: Python :: 3
Requires-Python: >=3.9
License-File: LICENSE
Requires-Dist: numpy
Requires-Dist: matplotlib (>=3.5.2)
Provides-Extra: dev
Requires-Dist: pip-tools ; extra == 'dev'
